[
  { "url": "https://bangla.bdnews24.com/sport" },
  { "url": "https://bangla.bdnews24.com/opinion" },
  { "url": "https://bangla.bdnews24.com/arts" },
  { "url": "https://bangla.bdnews24.com/glitz" },
  { "url": "https://bangla.bdnews24.com/lifestyle" },
  { "url": "https://bangla.bdnews24.com/tech" },
  { "url": "https://twitter.com/bdnews24com" },
  { "url": "https://www.facebook.com/bdnews24/" },
  { "url": "https://www.youtube.com/user/bdnews24DOTcom" },
  { "url": "https://www.instagram.com/bdnews24/" },
  { "url": "https://apps.apple.com/us/app/bdnews24/id560835088" },
  {
    "url": "https://play.google.com/store/apps/details?id=com.bdnews24.app&hl=en"
  },
  { "url": "https://bangla.bdnews24.com/" },
  { "url": "https://bdnews24.com/" },
  { "url": "https://bdnews24.com/" },
  { "url": "https://bangla.bdnews24.com/" },
  { "url": "https://bangla.bdnews24.com/samagrabangladesh" },
  { "url": "https://bangla.bdnews24.com/world" },
  { "url": "https://bangla.bdnews24.com/sport/world-cup-2022" },
  { "url": "https://bangla.bdnews24.com/cricket/t20wc2022" },
  { "url": "https://bangla.bdnews24.com/business" },
  { "url": "https://hello.bdnews24.com/" },
  { "url": "https://bangla.bdnews24.com/blog" },
  { "url": "https://bangla.bdnews24.com/tube" },
  { "url": "https://bangla.bdnews24.com/collection/111686" },
  { "url": "https://bangla.bdnews24.com/economy/bqhq8tz7ik" },
  { "url": "https://bangla.bdnews24.com/coronavirus-pandemic/xlkm5jn3ux" },
  { "url": "https://bangla.bdnews24.com/politics/c7k0yx7yfb" },
  { "url": "https://bangla.bdnews24.com/samagrabangladesh/gtlyv6lega" },
  { "url": "https://bangla.bdnews24.com/samagrabangladesh/78b6wt1nle" },
  { "url": "https://bangla.bdnews24.com/ctg/gaokwph4aj" },
  { "url": "https://bangla.bdnews24.com/world/cdk7vnefki" },
  { "url": "https://bangla.bdnews24.com/world/mwje1jq0jn" },
  { "url": "https://bangla.bdnews24.com/cricket/t20wc2022/zij0o2x534" },
  { "url": "https://bangla.bdnews24.com/cricket/t20wc2022/zij0o2x534" },
  { "url": "https://bangla.bdnews24.com/world/osdzlu75ei" },
  { "url": "https://bangla.bdnews24.com/world/osdzlu75ei" },
  { "url": "https://bangla.bdnews24.com/sport/c13vjby0vz" },
  { "url": "https://bangla.bdnews24.com/world/qvx5v3iyoi" },
  { "url": "https://bangla.bdnews24.com/ctg/qapcmk5d2g" },
  { "url": "https://bangla.bdnews24.com/samagrabangladesh/qng9dn4b2y" },
  { "url": "https://bangla.bdnews24.com/coronavirus-pandemic/xlkm5jn3ux" },
  { "url": "https://bangla.bdnews24.com/world/ffqoaqgro4" },
  { "url": "https://bangla.bdnews24.com/samagrabangladesh/v5tv10qqlu" },
  { "url": "https://bangla.bdnews24.com/samagrabangladesh/v5tv10qqlu" },
  { "url": "https://bangla.bdnews24.com/glitz/5x70kvk35a" },
  { "url": "https://bangla.bdnews24.com/glitz/5x70kvk35a" },
  { "url": "https://bangla.bdnews24.com/tech/0x5z9rp63f" },
  { "url": "https://bangla.bdnews24.com/tech/0x5z9rp63f" },
  { "url": "https://bangla.bdnews24.com/cricket/t20wc2022/h5er0o1a0c" },
  { "url": "https://bangla.bdnews24.com/cricket/t20wc2022/h5er0o1a0c" },
  { "url": "https://bangla.bdnews24.com/business/xsn1r0bnan" },
  { "url": "https://bangla.bdnews24.com/business/xsn1r0bnan" },
  { "url": "https://bangla.bdnews24.com/samagrabangladesh/fsf8wd7n0y" },
  { "url": "https://bangla.bdnews24.com/samagrabangladesh/fsf8wd7n0y" },
  { "url": "https://bangla.bdnews24.com/arts/s0wi9wqqtw" },
  { "url": "https://bangla.bdnews24.com/arts/s0wi9wqqtw" },
  { "url": "https://bangla.bdnews24.com/world/s51k9pz9zc" },
  { "url": "https://bangla.bdnews24.com/world/s51k9pz9zc" },
  { "url": "https://bangla.bdnews24.com/cricket/t20wc2022" },
  { "url": "https://bangla.bdnews24.com/cricket/t20wc2022/l0jm3musw7" },
  { "url": "https://bangla.bdnews24.com/cricket/t20wc2022/5cy0yw1aj5" },
  { "url": "https://bangla.bdnews24.com/cricket/t20wc2022/rebxg3p3i3" },
  { "url": "https://bangla.bdnews24.com/cricket/t20wc2022/3tlbvwdvtf" },
  { "url": "https://bangla.bdnews24.com/cricket/t20wc2022/fn4fnsnpdw" },
  { "url": "https://bangla.bdnews24.com/collection/cricket-record" },
  { "url": "https://bangla.bdnews24.com/cricket/t20wc2022/team-profile" },
  { "url": "https://bangla.bdnews24.com/cricket/t20wc2022/eszqmkipxh" },
  { "url": "https://bangla.bdnews24.com/cricket/t20wc2022/ciw7rbxtzl" },
  { "url": "https://bangla.bdnews24.com/cricket/t20wc2022/ciw7rbxtzl" },
  { "url": "https://bangla.bdnews24.com/cricket/t20wc2022/9lzt7kv1nf" },
  { "url": "https://bangla.bdnews24.com/cricket/t20wc2022/9lzt7kv1nf" },
  { "url": "https://bangla.bdnews24.com/cricket/t20wc2022/xuxkd7a6nt" },
  { "url": "https://bangla.bdnews24.com/cricket/t20wc2022/xuxkd7a6nt" },
  { "url": "https://bangla.bdnews24.com/cricket/t20wc2022/h5er0o1a0c" },
  { "url": "https://bangla.bdnews24.com/cricket/t20wc2022/h5er0o1a0c" },
  { "url": "https://bangla.bdnews24.com/cricket/t20wc2022/97vfjzv7wd" },
  { "url": "https://bangla.bdnews24.com/cricket/t20wc2022/97vfjzv7wd" },
  { "url": "https://bangla.bdnews24.com/cricket/t20wc2022/hqg99r79cj" },
  { "url": "https://bangla.bdnews24.com/cricket/t20wc2022/hqg99r79cj" },
  { "url": "https://bangla.bdnews24.com/cricket/t20wc2022/ao93qdr2ze" },
  { "url": "https://bangla.bdnews24.com/cricket/t20wc2022/ao93qdr2ze" },
  { "url": "https://bangla.bdnews24.com/cricket/t20wc2022/r6nn1ty8a5" },
  { "url": "https://bangla.bdnews24.com/cricket/t20wc2022/r6nn1ty8a5" },
  { "url": "https://bangla.bdnews24.com/glitz/5x70kvk35a" },
  { "url": "https://bangla.bdnews24.com/cricket/t20wc2022/9lzt7kv1nf" },
  { "url": "https://bangla.bdnews24.com/cricket/t20wc2022/xuxkd7a6nt" },
  { "url": "https://bangla.bdnews24.com/sport/c13vjby0vz" },
  { "url": "https://bangla.bdnews24.com/world/qvx5v3iyoi" },
  { "url": "https://bangla.bdnews24.com/samagrabangladesh/v5tv10qqlu" },
  { "url": "https://bangla.bdnews24.com/sport" },
  { "url": "https://bangla.bdnews24.com/sport/world-cup-2022/tpii9v057p" },
  { "url": "https://bangla.bdnews24.com/sport/world-cup-2022/tpii9v057p" },
  { "url": "https://bangla.bdnews24.com/sport/c13vjby0vz" },
  { "url": "https://bangla.bdnews24.com/sport/c13vjby0vz" },
  { "url": "https://bangla.bdnews24.com/sport/world-cup-2022/pl50kmgl28" },
  { "url": "https://bangla.bdnews24.com/sport/world-cup-2022/pl50kmgl28" },
  { "url": "https://bangla.bdnews24.com/sport/f4zfkrjgoi" },
  { "url": "https://bangla.bdnews24.com/sport/f4zfkrjgoi" },
  { "url": "https://bangla.bdnews24.com/sport/2wi7up7fz1" },
  { "url": "https://bangla.bdnews24.com/sport/2wi7up7fz1" },
  { "url": "https://bangla.bdnews24.com/sport/world-cup-2022/rf9c3l2ia3" },
  { "url": "https://bangla.bdnews24.com/sport/world-cup-2022/rf9c3l2ia3" },
  { "url": "https://bangla.bdnews24.com/sport" },
  { "url": "https://bangla.bdnews24.com/opinion" },
  { "url": "https://bangla.bdnews24.com/author/bibhurnyjn-srkaar-2" },
  { "url": "https://bangla.bdnews24.com/opinion/2d6bvi7dd6" },
  { "url": "https://bangla.bdnews24.com/author/bibhurnyjn-srkaar-2" },
  { "url": "https://bangla.bdnews24.com/author/ajyy-daashgupt" },
  { "url": "https://bangla.bdnews24.com/opinion/cng1foq6as" },
  { "url": "https://bangla.bdnews24.com/author/ajyy-daashgupt" },
  { "url": "https://bangla.bdnews24.com/author/en-aai-aahmed-saikt" },
  { "url": "https://bangla.bdnews24.com/opinion/4rt5u9ou8z" },
  { "url": "https://bangla.bdnews24.com/author/en-aai-aahmed-saikt" },
  { "url": "https://bangla.bdnews24.com/author/maahiul-kaadir" },
  { "url": "https://bangla.bdnews24.com/opinion/ycxqm1ng57" },
  { "url": "https://bangla.bdnews24.com/author/maahiul-kaadir" },
  { "url": "https://bangla.bdnews24.com/samagrabangladesh/nhbabkfao5" },
  { "url": "https://bangla.bdnews24.com/samagrabangladesh/nhbabkfao5" },
  { "url": "https://bangla.bdnews24.com/samagrabangladesh/mdtpgac1fl" },
  { "url": "https://bangla.bdnews24.com/samagrabangladesh/mdtpgac1fl" },
  { "url": "https://bangla.bdnews24.com/samagrabangladesh/qng9dn4b2y" },
  { "url": "https://bangla.bdnews24.com/samagrabangladesh/qng9dn4b2y" },
  { "url": "https://bangla.bdnews24.com/samagrabangladesh/yynpgnjhrz" },
  { "url": "https://bangla.bdnews24.com/samagrabangladesh/yynpgnjhrz" },
  { "url": "https://bangla.bdnews24.com/samagrabangladesh/fsf8wd7n0y" },
  { "url": "https://bangla.bdnews24.com/samagrabangladesh/fsf8wd7n0y" },
  { "url": "https://bangla.bdnews24.com/samagrabangladesh/v5tv10qqlu" },
  { "url": "https://bangla.bdnews24.com/samagrabangladesh/v5tv10qqlu" },
  { "url": "https://bangla.bdnews24.com/samagrabangladesh" },
  { "url": "https://bangla.bdnews24.com/world" },
  { "url": "https://bangla.bdnews24.com/world/qvx5v3iyoi" },
  { "url": "https://bangla.bdnews24.com/world/qvx5v3iyoi" },
  { "url": "https://bangla.bdnews24.com/world/osdzlu75ei" },
  { "url": "https://bangla.bdnews24.com/world/osdzlu75ei" },
  { "url": "https://bangla.bdnews24.com/world/ffqoaqgro4" },
  { "url": "https://bangla.bdnews24.com/world/ffqoaqgro4" },
  { "url": "https://bangla.bdnews24.com/world/z3mrhnxaa5" },
  { "url": "https://bangla.bdnews24.com/world/z3mrhnxaa5" },
  { "url": "https://bangla.bdnews24.com/world/17k8a1zy66" },
  { "url": "https://bangla.bdnews24.com/world/17k8a1zy66" },
  { "url": "https://bangla.bdnews24.com/world/cdk7vnefki" },
  { "url": "https://bangla.bdnews24.com/world/cdk7vnefki" },
  { "url": "https://bangla.bdnews24.com/world" },
  { "url": "https://bangla.bdnews24.com/tech" },
  { "url": "https://bangla.bdnews24.com/tech/iz1pxmtjoh" },
  { "url": "https://bangla.bdnews24.com/tech/iz1pxmtjoh" },
  { "url": "https://bangla.bdnews24.com/tech/0x5z9rp63f" },
  { "url": "https://bangla.bdnews24.com/tech/0x5z9rp63f" },
  { "url": "https://bangla.bdnews24.com/tech/owqt8g8t87" },
  { "url": "https://bangla.bdnews24.com/tech/owqt8g8t87" },
  { "url": "https://bangla.bdnews24.com/tech/n67ve3nxn2" },
  { "url": "https://bangla.bdnews24.com/tech/n67ve3nxn2" },
  { "url": "https://bangla.bdnews24.com/tech/uqwp2pf596" },
  { "url": "https://bangla.bdnews24.com/tech/uqwp2pf596" },
  { "url": "https://bangla.bdnews24.com/tech/k2tpnhqzp3" },
  { "url": "https://bangla.bdnews24.com/tech/k2tpnhqzp3" },
  { "url": "https://bangla.bdnews24.com/tech/j7kck9pgw8" },
  { "url": "https://bangla.bdnews24.com/tech/j7kck9pgw8" },
  { "url": "https://bangla.bdnews24.com/tech/uecvofuo8a" },
  { "url": "https://bangla.bdnews24.com/tech/uecvofuo8a" },
  { "url": "https://bangla.bdnews24.com/glitz" },
  { "url": "https://bangla.bdnews24.com/glitz/5x70kvk35a" },
  { "url": "https://bangla.bdnews24.com/glitz/5x70kvk35a" },
  { "url": "https://bangla.bdnews24.com/glitz/2bubbwzo6v" },
  { "url": "https://bangla.bdnews24.com/glitz/2bubbwzo6v" },
  { "url": "https://bangla.bdnews24.com/glitz/o5psi151pb" },
  { "url": "https://bangla.bdnews24.com/glitz/o5psi151pb" },
  { "url": "https://bangla.bdnews24.com/glitz/59v2i39kua" },
  { "url": "https://bangla.bdnews24.com/glitz/59v2i39kua" },
  { "url": "https://bangla.bdnews24.com/glitz/hjc7d8ej7a" },
  { "url": "https://bangla.bdnews24.com/glitz/hjc7d8ej7a" },
  { "url": "https://bangla.bdnews24.com/glitz/j89j5ralxa" },
  { "url": "https://bangla.bdnews24.com/glitz/j89j5ralxa" },
  { "url": "https://bangla.bdnews24.com/glitz" },
  { "url": "https://bangla.bdnews24.com/lifestyle" },
  { "url": "https://bangla.bdnews24.com/lifestyle/b7uf7s7ct3" },
  { "url": "https://bangla.bdnews24.com/lifestyle/b7uf7s7ct3" },
  { "url": "https://bangla.bdnews24.com/lifestyle/3kfv3v5lm5" },
  { "url": "https://bangla.bdnews24.com/lifestyle/3kfv3v5lm5" },
  { "url": "https://bangla.bdnews24.com/lifestyle/Jenerakun/x0ri7sqc1y" },
  { "url": "https://bangla.bdnews24.com/lifestyle/Jenerakun/x0ri7sqc1y" },
  { "url": "https://bangla.bdnews24.com/lifestyle/j4zfeotkt8" },
  { "url": "https://bangla.bdnews24.com/lifestyle/j4zfeotkt8" },
  { "url": "https://bangla.bdnews24.com/Jenerakun/qo6rgrj7m6" },
  { "url": "https://bangla.bdnews24.com/Jenerakun/qo6rgrj7m6" },
  { "url": "https://bangla.bdnews24.com/lifestyle/Jenerakun/4plu0aqncc" },
  { "url": "https://bangla.bdnews24.com/lifestyle/Jenerakun/4plu0aqncc" },
  { "url": "https://bangla.bdnews24.com/cricket" },
  { "url": "https://bangla.bdnews24.com/cricket/t20wc2022/ciw7rbxtzl" },
  { "url": "https://bangla.bdnews24.com/cricket/t20wc2022/ciw7rbxtzl" },
  { "url": "https://bangla.bdnews24.com/cricket/t20wc2022/9lzt7kv1nf" },
  { "url": "https://bangla.bdnews24.com/cricket/t20wc2022/9lzt7kv1nf" },
  { "url": "https://bangla.bdnews24.com/cricket/hpzb082meh" },
  { "url": "https://bangla.bdnews24.com/cricket/hpzb082meh" },
  { "url": "https://bangla.bdnews24.com/cricket/t20wc2022/xuxkd7a6nt" },
  { "url": "https://bangla.bdnews24.com/cricket/t20wc2022/xuxkd7a6nt" },
  { "url": "https://bangla.bdnews24.com/cricket/t20wc2022/h5er0o1a0c" },
  { "url": "https://bangla.bdnews24.com/cricket/t20wc2022/h5er0o1a0c" },
  { "url": "https://www.facebook.com/bdnews24" },
  { "url": "https://www.linkedin.com/company/bangladesh-news-24-hours-ltd" },
  { "url": "https://twitter.com/bdnews24com" },
  { "url": "https://bangla.bdnews24.com/" },
  { "url": "https://bangla.bdnews24.com/" },
  { "url": "https://bangla.bdnews24.com/bangladesh" },
  { "url": "https://bangla.bdnews24.com/business" },
  { "url": "https://bangla.bdnews24.com/politics" },
  { "url": "https://bangla.bdnews24.com/economy" },
  { "url": "https://bangla.bdnews24.com/world" },
  { "url": "https://bangla.bdnews24.com/science" },
  { "url": "https://bangla.bdnews24.com/environment" },
  { "url": "https://bangla.bdnews24.com/health" },
  { "url": "https://bangla.bdnews24.com/probash" },
  { "url": "https://bangla.bdnews24.com/tech" },
  { "url": "https://bangla.bdnews24.com/lifestyle" },
  { "url": "https://bangla.bdnews24.com/kidz" },
  { "url": "https://bangla.bdnews24.com/glitz" },
  { "url": "https://bangla.bdnews24.com/opinion" },
  { "url": "https://bangla.bdnews24.com/sport" },
  { "url": "https://bangla.bdnews24.com/cricket" },
  { "url": "https://bangla.bdnews24.com/blog" },
  { "url": "https://hello.bdnews24.com/" },
  { "url": "https://bangla.bdnews24.com/tube" },
  { "url": "https://bangla.bdnews24.com/mobile" },
  { "url": "https://bangla.bdnews24.com/gallery" },
  { "url": "https://twitter.com/bdnews24com" },
  { "url": "https://www.facebook.com/bdnews24/" },
  { "url": "https://www.youtube.com/user/bdnews24DOTcom" },
  { "url": "https://www.instagram.com/bdnews24/" },
  { "url": "https://bangla.bdnews24.com/disclaimer" },
  { "url": "https://bangla.bdnews24.com/about-us" },
  { "url": "https://bangla.bdnews24.com/contact" },
  { "url": "https://apps.apple.com/us/app/bdnews24/id560835088" },
  {
    "url": "https://play.google.com/store/apps/details?id=com.bdnews24.app&hl=en"
  }
]
